{
    "product": [
        {
            "title": "Picked for you",
            "menu": [
                {
                    "name": "Jumbo Fruits Party \u4e00\u6876\u6c34\u679c\u8336(1000ml)",
                    "price": "$12.65",
                    "description": "Include: Fresh Pineapple Jam, Watermelon, Mango Dice, Passion Fruit, Lime, Jasmine Tea."
                }
            ]
        },
        {
            "title": "Picked for you",
            "menu": [
                {
                    "name": "Jumbo Fruits Party \u4e00\u6876\u6c34\u679c\u8336(1000ml)",
                    "price": "$12.65",
                    "description": "Include: Fresh Pineapple Jam, Watermelon, Mango Dice, Passion Fruit, Lime, Jasmine Tea."
                }
            ]
        },
        {
            "title": "Picked for you",
            "menu": [
                {
                    "name": "Grape Jello Meet Taro Balls \u8461\u8404\u828b\u5706\u51bb\u51bb(700ml)",
                    "price": "$9.15",
                    "description": "Include: Jasmine Tea, Fig Jelly, Taro Balls,  Coconut Jelly, Grapefruit and Grape Juice.To keep the best quality and taste, \u201cno sugar\u201d is not optional, for the ice level of this item, \"no ice\" is not optional! (\u975e\u5e38\u62b1\u6b49\uff0c\u4e3a\u4e86\u4fdd\u8bc1\u8fd9\u6b3e\u4ea7\u54c1\u7684\u54c1\u8d28\u548c\u5473\u9053\uff0c\u6211\u4eec\u4e0d\u80fd\u5b8c\u5168\u53bb\u7cd6\u548c\u5b8c\u5168\u53bb\u51b0\uff0c\u4f46\u5982\u679c\u60a8\u6709\u7279\u6b8a\u8981\u6c42\u6211\u4eec\u53ef\u4ee5\u4e3a\u60a8\u5c3d\u91cf\u5c11\u7cd6\u4e0e\u5c11\u51b0!)"
                }
            ]
        },
        {
            "title": "Picked for you",
            "menu": [
                {
                    "name": "Grape Jello Meet Taro Balls \u8461\u8404\u828b\u5706\u51bb\u51bb(700ml)",
                    "price": "$9.15",
                    "description": "Include: Jasmine Tea, Fig Jelly, Taro Balls,  Coconut Jelly, Grapefruit and Grape Juice.To keep the best quality and taste, \u201cno sugar\u201d is not optional, for the ice level of this item, \"no ice\" is not optional! (\u975e\u5e38\u62b1\u6b49\uff0c\u4e3a\u4e86\u4fdd\u8bc1\u8fd9\u6b3e\u4ea7\u54c1\u7684\u54c1\u8d28\u548c\u5473\u9053\uff0c\u6211\u4eec\u4e0d\u80fd\u5b8c\u5168\u53bb\u7cd6\u548c\u5b8c\u5168\u53bb\u51b0\uff0c\u4f46\u5982\u679c\u60a8\u6709\u7279\u6b8a\u8981\u6c42\u6211\u4eec\u53ef\u4ee5\u4e3a\u60a8\u5c3d\u91cf\u5c11\u7cd6\u4e0e\u5c11\u51b0!)"
                }
            ]
        },
        {
            "title": "Picked for you",
            "menu": [
                {
                    "name": "Watermelon Crush Tea \u591a\u8089\u897f\u74dc\u51b0\u8336",
                    "price": "$8.95",
                    "description": "Include: Coconut Jelly, Fresh Watermelon, Jasmine Tea."
                }
            ]
        },
        {
            "title": "Picked for you",
            "menu": [
                {
                    "name": "Watermelon Crush Tea \u591a\u8089\u897f\u74dc\u51b0\u8336",
                    "price": "$8.95",
                    "description": "Include: Coconut Jelly, Fresh Watermelon, Jasmine Tea."
                }
            ]
        },
        {
            "title": "Picked for you",
            "menu": [
                {
                    "name": "Mango Pomelo Sago \u6768\u679d\u7518\u9732",
                    "price": "$8.65",
                    "description": "Include: Crushed Mango, Coconut Milk, Grapefruit, Diced Mango and Sago"
                }
            ]
        },
        {
            "title": "Picked for you",
            "menu": [
                {
                    "name": "Mango Pomelo Sago \u6768\u679d\u7518\u9732",
                    "price": "$8.65",
                    "description": "Include: Crushed Mango, Coconut Milk, Grapefruit, Diced Mango and Sago"
                }
            ]
        },
        {
            "title": "Picked for you",
            "menu": [
                {
                    "name": "Mango Pomelo Yogurt \u6768\u679d\u7518\u9732\u9178\u5976(700ml)",
                    "price": "$8.45",
                    "description": "Include: Jasmine Yogurt, Fig Jelly, Mango Dice, Sago, Mango Coconut Milk and Grapefruit."
                }
            ]
        },
        {
            "title": "Picked for you",
            "menu": [
                {
                    "name": "Mango Pomelo Yogurt \u6768\u679d\u7518\u9732\u9178\u5976(700ml)",
                    "price": "$8.45",
                    "description": "Include: Jasmine Yogurt, Fig Jelly, Mango Dice, Sago, Mango Coconut Milk and Grapefruit."
                }
            ]
        },
        {
            "title": "Super Save Combo (\u8d85\u503c\u4f18\u60e0\u5957\u9910)",
            "menu": [
                {
                    "name": "Taro Balls Lover",
                    "price": "$15.55",
                    "description": "Taro Balls Grass Jelly Milk Tea (\u5c0f\u828b\u5706\u70e7\u4ed9\u8349): Milk Tea, Taro Balls, Coconut Jelly, Red Bean and Grass Jelly.Taro Balls Meet Brown Sugar (\u9ed1\u7cd6\u5c0f\u828b\u5706\u5976\u8336): Black tea based Milk tea, Taro Balls, Brown Sugar Jelly."
                }
            ]
        },
        {
            "title": "Super Save Combo (\u8d85\u503c\u4f18\u60e0\u5957\u9910)",
            "menu": [
                {
                    "name": "Taro Balls Lover",
                    "price": "$15.55",
                    "description": "Taro Balls Grass Jelly Milk Tea (\u5c0f\u828b\u5706\u70e7\u4ed9\u8349): Milk Tea, Taro Balls, Coconut Jelly, Red Bean and Grass Jelly.Taro Balls Meet Brown Sugar (\u9ed1\u7cd6\u5c0f\u828b\u5706\u5976\u8336): Black tea based Milk tea, Taro Balls, Brown Sugar Jelly."
                }
            ]
        },
        {
            "title": "Super Save Combo (\u8d85\u503c\u4f18\u60e0\u5957\u9910)",
            "menu": [
                {
                    "name": "Summer Tea-Licious",
                    "price": "$16.55",
                    "description": "Fresh Lime Iced Tea(\u7206\u6253\u67e0\u6aac\u51b0\u8336): Fig Jelly, Fresh Lime, Jasmine Tea.Watermelon Crush Tea(\u591a\u8089\u897f\u74dc\u51b0\u8336): Coconut Jelly, Fresh Watermelon, Jasmine Tea."
                }
            ]
        },
        {
            "title": "Super Save Combo (\u8d85\u503c\u4f18\u60e0\u5957\u9910)",
            "menu": [
                {
                    "name": "Summer Tea-Licious",
                    "price": "$16.55",
                    "description": "Fresh Lime Iced Tea(\u7206\u6253\u67e0\u6aac\u51b0\u8336): Fig Jelly, Fresh Lime, Jasmine Tea.Watermelon Crush Tea(\u591a\u8089\u897f\u74dc\u51b0\u8336): Coconut Jelly, Fresh Watermelon, Jasmine Tea."
                }
            ]
        },
        {
            "title": "Super Save Combo (\u8d85\u503c\u4f18\u60e0\u5957\u9910)",
            "menu": [
                {
                    "name": "Cheese Lover",
                    "price": "$20.25",
                    "description": "Mango Cheese Green Tea (\u829d\u58eb\u8292\u679c\u591a\u591a): Fresh Mango, Jasmine Tea, Cheese.Strawberry Cheese Green Tea (\u829d\u58eb\u8349\u8393\u591a\u591a) : Fig Jelly, Osmanthus Jelly, Fresh Strawberry, Jasmine Tea, Cheese."
                }
            ]
        },
        {
            "title": "Super Save Combo (\u8d85\u503c\u4f18\u60e0\u5957\u9910)",
            "menu": [
                {
                    "name": "Cheese Lover",
                    "price": "$20.25",
                    "description": "Mango Cheese Green Tea (\u829d\u58eb\u8292\u679c\u591a\u591a): Fresh Mango, Jasmine Tea, Cheese.Strawberry Cheese Green Tea (\u829d\u58eb\u8349\u8393\u591a\u591a) : Fig Jelly, Osmanthus Jelly, Fresh Strawberry, Jasmine Tea, Cheese."
                }
            ]
        },
        {
            "title": "Super Save Combo (\u8d85\u503c\u4f18\u60e0\u5957\u9910)",
            "menu": [
                {
                    "name": "Mulberry Fans",
                    "price": "$17.00",
                    "description": "Mulberry Green Tea \u6851\u845a\u8393\u8393\uff08M\uff09: Jasmine Tea, POPO, Fresh Mulberry, Fresh Strawberry, Fresh LimeRaw Coconut Mulberry \u751f\u6930\u6851\u845a\u8393\u8393: Jasmine Tea, Fresh Mulberry, Fresh Strawberry, Coconut Milk"
                }
            ]
        },
        {
            "title": "Super Save Combo (\u8d85\u503c\u4f18\u60e0\u5957\u9910)",
            "menu": [
                {
                    "name": "Mulberry Fans",
                    "price": "$17.00",
                    "description": "Mulberry Green Tea \u6851\u845a\u8393\u8393\uff08M\uff09: Jasmine Tea, POPO, Fresh Mulberry, Fresh Strawberry, Fresh LimeRaw Coconut Mulberry \u751f\u6930\u6851\u845a\u8393\u8393: Jasmine Tea, Fresh Mulberry, Fresh Strawberry, Coconut Milk"
                }
            ]
        },
        {
            "title": "Super Save Combo (\u8d85\u503c\u4f18\u60e0\u5957\u9910)",
            "menu": [
                {
                    "name": "Brown Sugar Family",
                    "price": "$13.80",
                    "description": "Brown Sugar Plant Milk \u9ed1\u7cd6\u73cd\u73e0\u690d\u7269\u4e73 : Plant based Milk, Brown Sugar TapiocaBrown Sugar High Aroma \u9ed1\u7cd6\u73cd\u73e0\u9e2d\u5c4e\u9999 : High Aroma Oolong Tea, Plant based Milk, Brown Sugar Tapioca"
                }
            ]
        },
        {
            "title": "Super Save Combo (\u8d85\u503c\u4f18\u60e0\u5957\u9910)",
            "menu": [
                {
                    "name": "Brown Sugar Family",
                    "price": "$13.80",
                    "description": "Brown Sugar Plant Milk \u9ed1\u7cd6\u73cd\u73e0\u690d\u7269\u4e73 : Plant based Milk, Brown Sugar TapiocaBrown Sugar High Aroma \u9ed1\u7cd6\u73cd\u73e0\u9e2d\u5c4e\u9999 : High Aroma Oolong Tea, Plant based Milk, Brown Sugar Tapioca"
                }
            ]
        },
        {
            "title": "New Arrival (\u65b0\u54c1\u4e0a\u7ebf)",
            "menu": [
                {
                    "name": "Orange Camellia Oat Milk \u6a59\u6f2b\u5c71\u8336\u82b1(500ml)",
                    "price": "$7.35",
                    "description": "Includes: Camellia Oolong Tea, Fresh Orange, Oat Milk, Plant Milk"
                }
            ]
        },
        {
            "title": "New Arrival (\u65b0\u54c1\u4e0a\u7ebf)",
            "menu": [
                {
                    "name": "Orange Camellia Oat Milk \u6a59\u6f2b\u5c71\u8336\u82b1(500ml)",
                    "price": "$7.35",
                    "description": "Includes: Camellia Oolong Tea, Fresh Orange, Oat Milk, Plant Milk"
                }
            ]
        },
        {
            "title": "New Arrival (\u65b0\u54c1\u4e0a\u7ebf)",
            "menu": [
                {
                    "name": "Chestnut Rose Yogurt \u523a\u68a8\u51bb\u51bb\u9178\u5976(500ml)",
                    "price": "$7.95",
                    "description": "Include: Jasmine Yogurt, Jasmine Tea, Chestnut Rose Juice and Chestnut Rose Jelly."
                }
            ]
        },
        {
            "title": "New Arrival (\u65b0\u54c1\u4e0a\u7ebf)",
            "menu": [
                {
                    "name": "Chestnut Rose Yogurt \u523a\u68a8\u51bb\u51bb\u9178\u5976(500ml)",
                    "price": "$7.95",
                    "description": "Include: Jasmine Yogurt, Jasmine Tea, Chestnut Rose Juice and Chestnut Rose Jelly."
                }
            ]
        },
        {
            "title": "New Arrival (\u65b0\u54c1\u4e0a\u7ebf)",
            "menu": [
                {
                    "name": "Rich VC Yogurt \u7ef4C\u4ed9\u8349\u9178\u5976(500ml)",
                    "price": "$7.95",
                    "description": "Include: Jasmine Yogurt, Jasmine Tea, Chestnut Rose Juice and Grass Jelly."
                }
            ]
        },
        {
            "title": "New Arrival (\u65b0\u54c1\u4e0a\u7ebf)",
            "menu": [
                {
                    "name": "Rich VC Yogurt \u7ef4C\u4ed9\u8349\u9178\u5976(500ml)",
                    "price": "$7.95",
                    "description": "Include: Jasmine Yogurt, Jasmine Tea, Chestnut Rose Juice and Grass Jelly."
                }
            ]
        },
        {
            "title": "New Arrival (\u65b0\u54c1\u4e0a\u7ebf)",
            "menu": [
                {
                    "name": "Camellia Oat Latte \u5c71\u8336\u82b1\u71d5\u9ea6\u62ff\u94c1(500ml)",
                    "price": "$7.35",
                    "description": "Includes: Camellia Oolong Tea, Oat Milk"
                }
            ]
        },
        {
            "title": "New Arrival (\u65b0\u54c1\u4e0a\u7ebf)",
            "menu": [
                {
                    "name": "Camellia Oat Latte \u5c71\u8336\u82b1\u71d5\u9ea6\u62ff\u94c1(500ml)",
                    "price": "$7.35",
                    "description": "Includes: Camellia Oolong Tea, Oat Milk"
                }
            ]
        },
        {
            "title": "Top List (\u70ed\u9500\u6392\u884c\u699c)",
            "menu": [
                {
                    "name": "Jumbo Fruits Party \u4e00\u6876\u6c34\u679c\u8336(1000ml)",
                    "price": "$12.65",
                    "description": "Include: Fresh Pineapple Jam, Watermelon, Mango Dice, Passion Fruit, Lime, Jasmine Tea."
                }
            ]
        },
        {
            "title": "Top List (\u70ed\u9500\u6392\u884c\u699c)",
            "menu": [
                {
                    "name": "Jumbo Fruits Party \u4e00\u6876\u6c34\u679c\u8336(1000ml)",
                    "price": "$12.65",
                    "description": "Include: Fresh Pineapple Jam, Watermelon, Mango Dice, Passion Fruit, Lime, Jasmine Tea."
                }
            ]
        },
        {
            "title": "Top List (\u70ed\u9500\u6392\u884c\u699c)",
            "menu": [
                {
                    "name": "Signature Grass Jelly Milk Tea \u4e66\u4ea6\u70e7\u4ed9\u8349",
                    "price": "$7.95",
                    "description": "Include: Milk Tea, Grass Jelly, Coconut Jelly, Red Bean, Raisins, Tapioca.Sorry for this item, the sugar level is fixed. (\u975e\u5e38\u62b1\u6b49\uff0c\u8fd9\u4e00\u6b3e\u4ea7\u54c1\u7cd6\u5ea6\u4e0d\u80fd\u8c03\u6574.)"
                }
            ]
        },
        {
            "title": "Top List (\u70ed\u9500\u6392\u884c\u699c)",
            "menu": [
                {
                    "name": "Signature Grass Jelly Milk Tea \u4e66\u4ea6\u70e7\u4ed9\u8349",
                    "price": "$7.95",
                    "description": "Include: Milk Tea, Grass Jelly, Coconut Jelly, Red Bean, Raisins, Tapioca.Sorry for this item, the sugar level is fixed. (\u975e\u5e38\u62b1\u6b49\uff0c\u8fd9\u4e00\u6b3e\u4ea7\u54c1\u7cd6\u5ea6\u4e0d\u80fd\u8c03\u6574.)"
                }
            ]
        },
        {
            "title": "Top List (\u70ed\u9500\u6392\u884c\u699c)",
            "menu": [
                {
                    "name": "Strawberry POPO Yogurt \u8349\u8393\u5575\u5575\u9178\u5976 (700ml)",
                    "price": "$8.45",
                    "description": "Include: Jasmine Yogurt, Jasmine Tea, Fig Jelly, POPO and Fresh Strawberry."
                }
            ]
        },
        {
            "title": "Top List (\u70ed\u9500\u6392\u884c\u699c)",
            "menu": [
                {
                    "name": "Strawberry POPO Yogurt \u8349\u8393\u5575\u5575\u9178\u5976 (700ml)",
                    "price": "$8.45",
                    "description": "Include: Jasmine Yogurt, Jasmine Tea, Fig Jelly, POPO and Fresh Strawberry."
                }
            ]
        },
        {
            "title": "Top List (\u70ed\u9500\u6392\u884c\u699c)",
            "menu": [
                {
                    "name": "Mango Pomelo Yogurt \u6768\u679d\u7518\u9732\u9178\u5976(700ml)",
                    "price": "$8.45",
                    "description": "Include: Jasmine Yogurt, Fig Jelly, Mango Dice, Sago, Mango Coconut Milk and Grapefruit."
                }
            ]
        },
        {
            "title": "Top List (\u70ed\u9500\u6392\u884c\u699c)",
            "menu": [
                {
                    "name": "Mango Pomelo Yogurt \u6768\u679d\u7518\u9732\u9178\u5976(700ml)",
                    "price": "$8.45",
                    "description": "Include: Jasmine Yogurt, Fig Jelly, Mango Dice, Sago, Mango Coconut Milk and Grapefruit."
                }
            ]
        },
        {
            "title": "Milk Tea (\u4e66\u4ea6\uff0d\u7ecf\u5178\u5976\u8336)",
            "menu": [
                {
                    "name": "Camellia Oat Latte \u5c71\u8336\u82b1\u71d5\u9ea6\u62ff\u94c1(500ml)",
                    "price": "$7.35",
                    "description": "Includes: Camellia Oolong Tea, Oat Milk"
                }
            ]
        },
        {
            "title": "Milk Tea (\u4e66\u4ea6\uff0d\u7ecf\u5178\u5976\u8336)",
            "menu": [
                {
                    "name": "Camellia Oat Latte \u5c71\u8336\u82b1\u71d5\u9ea6\u62ff\u94c1(500ml)",
                    "price": "$7.35",
                    "description": "Includes: Camellia Oolong Tea, Oat Milk"
                }
            ]
        },
        {
            "title": "Milk Tea (\u4e66\u4ea6\uff0d\u7ecf\u5178\u5976\u8336)",
            "menu": [
                {
                    "name": "Signature Bubble Tea \u62db\u724c\u73cd\u73e0\u5976\u8336",
                    "price": "$7.95",
                    "description": "Include: Black tea based Milk tea, Tapioca"
                }
            ]
        },
        {
            "title": "Milk Tea (\u4e66\u4ea6\uff0d\u7ecf\u5178\u5976\u8336)",
            "menu": [
                {
                    "name": "Signature Bubble Tea \u62db\u724c\u73cd\u73e0\u5976\u8336",
                    "price": "$7.95",
                    "description": "Include: Black tea based Milk tea, Tapioca"
                }
            ]
        },
        {
            "title": "Milk Tea (\u4e66\u4ea6\uff0d\u7ecf\u5178\u5976\u8336)",
            "menu": [
                {
                    "name": "Brown Sugar Plant Milk \u9ed1\u7cd6\u73cd\u73e0\u690d\u7269\u4e73(500ml)",
                    "price": "$7.35",
                    "description": "Includes: Plant based Milk, Brown Sugar Tapioca"
                }
            ]
        },
        {
            "title": "Milk Tea (\u4e66\u4ea6\uff0d\u7ecf\u5178\u5976\u8336)",
            "menu": [
                {
                    "name": "Brown Sugar Plant Milk \u9ed1\u7cd6\u73cd\u73e0\u690d\u7269\u4e73(500ml)",
                    "price": "$7.35",
                    "description": "Includes: Plant based Milk, Brown Sugar Tapioca"
                }
            ]
        },
        {
            "title": "Milk Tea (\u4e66\u4ea6\uff0d\u7ecf\u5178\u5976\u8336)",
            "menu": [
                {
                    "name": "Mango Coconut Taro Balls \u8292\u6930\u5c0f\u4e38\u5b50 (500ml)",
                    "price": "$8.45",
                    "description": "Include: Coconut Milk, Rich Cream, Diced Mango, Taro Balls and Sago"
                }
            ]
        },
        {
            "title": "Milk Tea (\u4e66\u4ea6\uff0d\u7ecf\u5178\u5976\u8336)",
            "menu": [
                {
                    "name": "Mango Coconut Taro Balls \u8292\u6930\u5c0f\u4e38\u5b50 (500ml)",
                    "price": "$8.45",
                    "description": "Include: Coconut Milk, Rich Cream, Diced Mango, Taro Balls and Sago"
                }
            ]
        },
        {
            "title": "Milk Tea (\u4e66\u4ea6\uff0d\u7ecf\u5178\u5976\u8336)",
            "menu": [
                {
                    "name": "Royal No 1 Milk Tea \u725b\u9b54\u738b\u9ed1\u7816\u5976\u8336",
                    "price": "$8.75",
                    "description": "Include: Royal No.1 Blend Milk Tea, Brown Sugar Jelly"
                }
            ]
        },
        {
            "title": "Milk Tea (\u4e66\u4ea6\uff0d\u7ecf\u5178\u5976\u8336)",
            "menu": [
                {
                    "name": "Royal No 1 Milk Tea \u725b\u9b54\u738b\u9ed1\u7816\u5976\u8336",
                    "price": "$8.75",
                    "description": "Include: Royal No.1 Blend Milk Tea, Brown Sugar Jelly"
                }
            ]
        },
        {
            "title": "Milk Tea (\u4e66\u4ea6\uff0d\u7ecf\u5178\u5976\u8336)",
            "menu": [
                {
                    "name": "Taro Balls Meet Brown Sugar \u9ed1\u7cd6\u5c0f\u828b\u5706\u5976\u8336",
                    "price": "$8.75",
                    "description": "Include: Black tea based Milk tea, Taro Balls, Brown Sugar Jelly"
                }
            ]
        },
        {
            "title": "Milk Tea (\u4e66\u4ea6\uff0d\u7ecf\u5178\u5976\u8336)",
            "menu": [
                {
                    "name": "Taro Balls Meet Brown Sugar \u9ed1\u7cd6\u5c0f\u828b\u5706\u5976\u8336",
                    "price": "$8.75",
                    "description": "Include: Black tea based Milk tea, Taro Balls, Brown Sugar Jelly"
                }
            ]
        },
        {
            "title": "Milk Tea (\u4e66\u4ea6\uff0d\u7ecf\u5178\u5976\u8336)",
            "menu": [
                {
                    "name": "Happy Taro Milk Tea \u828b\u6ce5\u5168\u5bb6\u798f(500ml)",
                    "price": "$8.35",
                    "description": "Include: Jasmine Tea Based Milk Tea, Mashed Taro, Taro Balls, Sago"
                }
            ]
        },
        {
            "title": "Milk Tea (\u4e66\u4ea6\uff0d\u7ecf\u5178\u5976\u8336)",
            "menu": [
                {
                    "name": "Happy Taro Milk Tea \u828b\u6ce5\u5168\u5bb6\u798f(500ml)",
                    "price": "$8.35",
                    "description": "Include: Jasmine Tea Based Milk Tea, Mashed Taro, Taro Balls, Sago"
                }
            ]
        },
        {
            "title": "Milk Tea (\u4e66\u4ea6\uff0d\u7ecf\u5178\u5976\u8336)",
            "menu": [
                {
                    "name": "Caramel Bubble Milk Tea \u7126\u7cd6\u73cd\u73e0\u5976\u8336",
                    "price": "$7.95",
                    "description": "Include: Black tea based Milk tea, Caramel, Tapioca"
                }
            ]
        },
        {
            "title": "Milk Tea (\u4e66\u4ea6\uff0d\u7ecf\u5178\u5976\u8336)",
            "menu": [
                {
                    "name": "Caramel Bubble Milk Tea \u7126\u7cd6\u73cd\u73e0\u5976\u8336",
                    "price": "$7.95",
                    "description": "Include: Black tea based Milk tea, Caramel, Tapioca"
                }
            ]
        },
        {
            "title": "Milk Tea (\u4e66\u4ea6\uff0d\u7ecf\u5178\u5976\u8336)",
            "menu": [
                {
                    "name": "Mango Coconut Mashed Taro \u8292\u6930\u828b\u6ce5\u7ef5\u7ef5 (500ml)",
                    "price": "$8.45",
                    "description": "Include: Coconut Milk, Thick Milk, Diced Mango, Mashed Taro and Sago"
                }
            ]
        },
        {
            "title": "Milk Tea (\u4e66\u4ea6\uff0d\u7ecf\u5178\u5976\u8336)",
            "menu": [
                {
                    "name": "Mango Coconut Mashed Taro \u8292\u6930\u828b\u6ce5\u7ef5\u7ef5 (500ml)",
                    "price": "$8.45",
                    "description": "Include: Coconut Milk, Thick Milk, Diced Mango, Mashed Taro and Sago"
                }
            ]
        },
        {
            "title": "Grass Jelly (\u4e66\u4ea6-\u5f53\u5bb6\u70e7\u4ed9\u8349)",
            "menu": [
                {
                    "name": "Signature Grass Jelly Milk Tea \u4e66\u4ea6\u70e7\u4ed9\u8349",
                    "price": "$7.95",
                    "description": "Include: Milk Tea, Grass Jelly, Coconut Jelly, Red Bean, Raisins, Tapioca.Sorry for this item, the sugar level is fixed. (\u975e\u5e38\u62b1\u6b49\uff0c\u8fd9\u4e00\u6b3e\u4ea7\u54c1\u7cd6\u5ea6\u4e0d\u80fd\u8c03\u6574.)"
                }
            ]
        },
        {
            "title": "Grass Jelly (\u4e66\u4ea6-\u5f53\u5bb6\u70e7\u4ed9\u8349)",
            "menu": [
                {
                    "name": "Signature Grass Jelly Milk Tea \u4e66\u4ea6\u70e7\u4ed9\u8349",
                    "price": "$7.95",
                    "description": "Include: Milk Tea, Grass Jelly, Coconut Jelly, Red Bean, Raisins, Tapioca.Sorry for this item, the sugar level is fixed. (\u975e\u5e38\u62b1\u6b49\uff0c\u8fd9\u4e00\u6b3e\u4ea7\u54c1\u7cd6\u5ea6\u4e0d\u80fd\u8c03\u6574.)"
                }
            ]
        },
        {
            "title": "Grass Jelly (\u4e66\u4ea6-\u5f53\u5bb6\u70e7\u4ed9\u8349)",
            "menu": [
                {
                    "name": "Rich VC Yogurt \u7ef4C\u4ed9\u8349\u9178\u5976(500ml)",
                    "price": "$7.95",
                    "description": "Include: Jasmine Yogurt, Jasmine Tea, Chestnut Rose Juice and Grass Jelly."
                }
            ]
        },
        {
            "title": "Grass Jelly (\u4e66\u4ea6-\u5f53\u5bb6\u70e7\u4ed9\u8349)",
            "menu": [
                {
                    "name": "Rich VC Yogurt \u7ef4C\u4ed9\u8349\u9178\u5976(500ml)",
                    "price": "$7.95",
                    "description": "Include: Jasmine Yogurt, Jasmine Tea, Chestnut Rose Juice and Grass Jelly."
                }
            ]
        },
        {
            "title": "Grass Jelly (\u4e66\u4ea6-\u5f53\u5bb6\u70e7\u4ed9\u8349)",
            "menu": [
                {
                    "name": "Coconut Grass Jelly Milk Tea \u6930\u6930\u70e7\u4ed9\u8349",
                    "price": "$7.25",
                    "description": "Include: Coconut Milk, Jasmine Tea, Grass Jelly and Tapioca"
                }
            ]
        },
        {
            "title": "Grass Jelly (\u4e66\u4ea6-\u5f53\u5bb6\u70e7\u4ed9\u8349)",
            "menu": [
                {
                    "name": "Coconut Grass Jelly Milk Tea \u6930\u6930\u70e7\u4ed9\u8349",
                    "price": "$7.25",
                    "description": "Include: Coconut Milk, Jasmine Tea, Grass Jelly and Tapioca"
                }
            ]
        },
        {
            "title": "Grass Jelly (\u4e66\u4ea6-\u5f53\u5bb6\u70e7\u4ed9\u8349)",
            "menu": [
                {
                    "name": "Taro Balls Grass Jelly Milk Tea \u5c0f\u828b\u5706\u70e7\u4ed9\u8349(500ml)",
                    "price": "$7.95",
                    "description": "Include: Milk Tea, Taro Balls, Coconut Jelly, Red Bean and Grass Jelly.Sorry for this item, the sugar level is fixed. (\u975e\u5e38\u62b1\u6b49\uff0c\u8fd9\u4e00\u6b3e\u4ea7\u54c1\u7cd6\u5ea6\u4e0d\u80fd\u8c03\u6574.)"
                }
            ]
        },
        {
            "title": "Grass Jelly (\u4e66\u4ea6-\u5f53\u5bb6\u70e7\u4ed9\u8349)",
            "menu": [
                {
                    "name": "Taro Balls Grass Jelly Milk Tea \u5c0f\u828b\u5706\u70e7\u4ed9\u8349(500ml)",
                    "price": "$7.95",
                    "description": "Include: Milk Tea, Taro Balls, Coconut Jelly, Red Bean and Grass Jelly.Sorry for this item, the sugar level is fixed. (\u975e\u5e38\u62b1\u6b49\uff0c\u8fd9\u4e00\u6b3e\u4ea7\u54c1\u7cd6\u5ea6\u4e0d\u80fd\u8c03\u6574.)"
                }
            ]
        },
        {
            "title": "Fresh Fruit Tea (\u4e66\u4ea6\uff0d\u56db\u5b63\u6c34\u679c\u8336)",
            "menu": [
                {
                    "name": "Jumbo Fruits Party \u4e00\u6876\u6c34\u679c\u8336(1000ml)",
                    "price": "$12.65",
                    "description": "Include: Fresh Pineapple Jam, Watermelon, Mango Dice, Passion Fruit, Lime, Jasmine Tea."
                }
            ]
        },
        {
            "title": "Fresh Fruit Tea (\u4e66\u4ea6\uff0d\u56db\u5b63\u6c34\u679c\u8336)",
            "menu": [
                {
                    "name": "Jumbo Fruits Party \u4e00\u6876\u6c34\u679c\u8336(1000ml)",
                    "price": "$12.65",
                    "description": "Include: Fresh Pineapple Jam, Watermelon, Mango Dice, Passion Fruit, Lime, Jasmine Tea."
                }
            ]
        },
        {
            "title": "Fresh Fruit Tea (\u4e66\u4ea6\uff0d\u56db\u5b63\u6c34\u679c\u8336)",
            "menu": [
                {
                    "name": "Watermelon Crush Tea \u591a\u8089\u897f\u74dc\u51b0\u8336",
                    "price": "$8.95",
                    "description": "Include: Coconut Jelly, Fresh Watermelon, Jasmine Tea."
                }
            ]
        },
        {
            "title": "Fresh Fruit Tea (\u4e66\u4ea6\uff0d\u56db\u5b63\u6c34\u679c\u8336)",
            "menu": [
                {
                    "name": "Watermelon Crush Tea \u591a\u8089\u897f\u74dc\u51b0\u8336",
                    "price": "$8.95",
                    "description": "Include: Coconut Jelly, Fresh Watermelon, Jasmine Tea."
                }
            ]
        },
        {
            "title": "Fresh Fruit Tea (\u4e66\u4ea6\uff0d\u56db\u5b63\u6c34\u679c\u8336)",
            "menu": [
                {
                    "name": "Grape Jello Meet Taro Balls \u8461\u8404\u828b\u5706\u51bb\u51bb(700ml)",
                    "price": "$9.15",
                    "description": "Include: Jasmine Tea, Fig Jelly, Taro Balls,  Coconut Jelly, Grapefruit and Grape Juice.To keep the best quality and taste, \u201cno sugar\u201d is not optional, for the ice level of this item, \"no ice\" is not optional! (\u975e\u5e38\u62b1\u6b49\uff0c\u4e3a\u4e86\u4fdd\u8bc1\u8fd9\u6b3e\u4ea7\u54c1\u7684\u54c1\u8d28\u548c\u5473\u9053\uff0c\u6211\u4eec\u4e0d\u80fd\u5b8c\u5168\u53bb\u7cd6\u548c\u5b8c\u5168\u53bb\u51b0\uff0c\u4f46\u5982\u679c\u60a8\u6709\u7279\u6b8a\u8981\u6c42\u6211\u4eec\u53ef\u4ee5\u4e3a\u60a8\u5c3d\u91cf\u5c11\u7cd6\u4e0e\u5c11\u51b0!)"
                }
            ]
        },
        {
            "title": "Fresh Fruit Tea (\u4e66\u4ea6\uff0d\u56db\u5b63\u6c34\u679c\u8336)",
            "menu": [
                {
                    "name": "Grape Jello Meet Taro Balls \u8461\u8404\u828b\u5706\u51bb\u51bb(700ml)",
                    "price": "$9.15",
                    "description": "Include: Jasmine Tea, Fig Jelly, Taro Balls,  Coconut Jelly, Grapefruit and Grape Juice.To keep the best quality and taste, \u201cno sugar\u201d is not optional, for the ice level of this item, \"no ice\" is not optional! (\u975e\u5e38\u62b1\u6b49\uff0c\u4e3a\u4e86\u4fdd\u8bc1\u8fd9\u6b3e\u4ea7\u54c1\u7684\u54c1\u8d28\u548c\u5473\u9053\uff0c\u6211\u4eec\u4e0d\u80fd\u5b8c\u5168\u53bb\u7cd6\u548c\u5b8c\u5168\u53bb\u51b0\uff0c\u4f46\u5982\u679c\u60a8\u6709\u7279\u6b8a\u8981\u6c42\u6211\u4eec\u53ef\u4ee5\u4e3a\u60a8\u5c3d\u91cf\u5c11\u7cd6\u4e0e\u5c11\u51b0!)"
                }
            ]
        },
        {
            "title": "Fresh Fruit Tea (\u4e66\u4ea6\uff0d\u56db\u5b63\u6c34\u679c\u8336)",
            "menu": [
                {
                    "name": "Mango Pomelo Sago \u6768\u679d\u7518\u9732",
                    "price": "$8.65",
                    "description": "Include: Crushed Mango, Coconut Milk, Grapefruit, Diced Mango and Sago"
                }
            ]
        },
        {
            "title": "Fresh Fruit Tea (\u4e66\u4ea6\uff0d\u56db\u5b63\u6c34\u679c\u8336)",
            "menu": [
                {
                    "name": "Mango Pomelo Sago \u6768\u679d\u7518\u9732",
                    "price": "$8.65",
                    "description": "Include: Crushed Mango, Coconut Milk, Grapefruit, Diced Mango and Sago"
                }
            ]
        },
        {
            "title": "Fresh Fruit Tea (\u4e66\u4ea6\uff0d\u56db\u5b63\u6c34\u679c\u8336)",
            "menu": [
                {
                    "name": "Orange Camellia Oat Milk \u6a59\u6f2b\u5c71\u8336\u82b1(500ml)",
                    "price": "$7.35",
                    "description": "Includes: Camellia Oolong Tea, Fresh Orange, Oat Milk, Plant Milk"
                }
            ]
        },
        {
            "title": "Fresh Fruit Tea (\u4e66\u4ea6\uff0d\u56db\u5b63\u6c34\u679c\u8336)",
            "menu": [
                {
                    "name": "Orange Camellia Oat Milk \u6a59\u6f2b\u5c71\u8336\u82b1(500ml)",
                    "price": "$7.35",
                    "description": "Includes: Camellia Oolong Tea, Fresh Orange, Oat Milk, Plant Milk"
                }
            ]
        },
        {
            "title": "Fresh Fruit Tea (\u4e66\u4ea6\uff0d\u56db\u5b63\u6c34\u679c\u8336)",
            "menu": [
                {
                    "name": "Strawberry POPO Yogurt \u8349\u8393\u5575\u5575\u9178\u5976 (700ml)",
                    "price": "$8.45",
                    "description": "Include: Jasmine Yogurt, Jasmine Tea, Fig Jelly, POPO and Fresh Strawberry."
                }
            ]
        },
        {
            "title": "Fresh Fruit Tea (\u4e66\u4ea6\uff0d\u56db\u5b63\u6c34\u679c\u8336)",
            "menu": [
                {
                    "name": "Strawberry POPO Yogurt \u8349\u8393\u5575\u5575\u9178\u5976 (700ml)",
                    "price": "$8.45",
                    "description": "Include: Jasmine Yogurt, Jasmine Tea, Fig Jelly, POPO and Fresh Strawberry."
                }
            ]
        },
        {
            "title": "Fresh Fruit Tea (\u4e66\u4ea6\uff0d\u56db\u5b63\u6c34\u679c\u8336)",
            "menu": [
                {
                    "name": "Mango Pomelo Yogurt \u6768\u679d\u7518\u9732\u9178\u5976(700ml)",
                    "price": "$8.45",
                    "description": "Include: Jasmine Yogurt, Fig Jelly, Mango Dice, Sago, Mango Coconut Milk and Grapefruit."
                }
            ]
        },
        {
            "title": "Fresh Fruit Tea (\u4e66\u4ea6\uff0d\u56db\u5b63\u6c34\u679c\u8336)",
            "menu": [
                {
                    "name": "Mango Pomelo Yogurt \u6768\u679d\u7518\u9732\u9178\u5976(700ml)",
                    "price": "$8.45",
                    "description": "Include: Jasmine Yogurt, Fig Jelly, Mango Dice, Sago, Mango Coconut Milk and Grapefruit."
                }
            ]
        },
        {
            "title": "Fresh Fruit Tea (\u4e66\u4ea6\uff0d\u56db\u5b63\u6c34\u679c\u8336)",
            "menu": [
                {
                    "name": "Chestnut Rose Yogurt \u523a\u68a8\u51bb\u51bb\u9178\u5976(500ml)",
                    "price": "$7.95",
                    "description": "Include: Jasmine Yogurt, Jasmine Tea, Chestnut Rose Juice and Chestnut Rose Jelly."
                }
            ]
        },
        {
            "title": "Fresh Fruit Tea (\u4e66\u4ea6\uff0d\u56db\u5b63\u6c34\u679c\u8336)",
            "menu": [
                {
                    "name": "Chestnut Rose Yogurt \u523a\u68a8\u51bb\u51bb\u9178\u5976(500ml)",
                    "price": "$7.95",
                    "description": "Include: Jasmine Yogurt, Jasmine Tea, Chestnut Rose Juice and Chestnut Rose Jelly."
                }
            ]
        },
        {
            "title": "Fresh Fruit Tea (\u4e66\u4ea6\uff0d\u56db\u5b63\u6c34\u679c\u8336)",
            "menu": [
                {
                    "name": "Fresh Lime Iced Tea \u7206\u6253\u67e0\u6aac\u51b0\u8336(700ml)",
                    "price": "$8.65",
                    "description": "Include: Fig Jelly, Fresh Lime, Jasmine Tea."
                }
            ]
        },
        {
            "title": "Fresh Fruit Tea (\u4e66\u4ea6\uff0d\u56db\u5b63\u6c34\u679c\u8336)",
            "menu": [
                {
                    "name": "Fresh Lime Iced Tea \u7206\u6253\u67e0\u6aac\u51b0\u8336(700ml)",
                    "price": "$8.65",
                    "description": "Include: Fig Jelly, Fresh Lime, Jasmine Tea."
                }
            ]
        },
        {
            "title": "Fresh Fruit Tea (\u4e66\u4ea6\uff0d\u56db\u5b63\u6c34\u679c\u8336)",
            "menu": [
                {
                    "name": "Grapefruit Yakult \u7ea2\u67da\u767d\u6708\u5149 (700ml)",
                    "price": "$9.15",
                    "description": "Include: Jasmine Tea, POPO, Fresh Grapefruit, Upgraded Yakult"
                }
            ]
        },
        {
            "title": "Fresh Fruit Tea (\u4e66\u4ea6\uff0d\u56db\u5b63\u6c34\u679c\u8336)",
            "menu": [
                {
                    "name": "Grapefruit Yakult \u7ea2\u67da\u767d\u6708\u5149 (700ml)",
                    "price": "$9.15",
                    "description": "Include: Jasmine Tea, POPO, Fresh Grapefruit, Upgraded Yakult"
                }
            ]
        },
        {
            "title": "Fresh Fruit Tea (\u4e66\u4ea6\uff0d\u56db\u5b63\u6c34\u679c\u8336)",
            "menu": [
                {
                    "name": "Chestnut Rose Green Tea \u523a\u68a8\u67e0\u6aac\u67da(500ml)",
                    "price": "$7.95",
                    "description": "Include: Jasmine Tea, Coconut Jelly, Chestnut Rose Juice, Fresh Lime, Fresh Grapefruit"
                }
            ]
        },
        {
            "title": "Fresh Fruit Tea (\u4e66\u4ea6\uff0d\u56db\u5b63\u6c34\u679c\u8336)",
            "menu": [
                {
                    "name": "Chestnut Rose Green Tea \u523a\u68a8\u67e0\u6aac\u67da(500ml)",
                    "price": "$7.95",
                    "description": "Include: Jasmine Tea, Coconut Jelly, Chestnut Rose Juice, Fresh Lime, Fresh Grapefruit"
                }
            ]
        },
        {
            "title": "Fresh Fruit Tea (\u4e66\u4ea6\uff0d\u56db\u5b63\u6c34\u679c\u8336)",
            "menu": [
                {
                    "name": "Pineapple & Passion Fruit POPO Tea \u767e\u9999\u51e4\u68a8\u5575\u5575\u8336",
                    "price": "$8.65",
                    "description": "Include: POPO, Fresh Pineapple Jam, Passion Fruit, Lime, Jasmine Tea."
                }
            ]
        },
        {
            "title": "Fresh Fruit Tea (\u4e66\u4ea6\uff0d\u56db\u5b63\u6c34\u679c\u8336)",
            "menu": [
                {
                    "name": "Pineapple & Passion Fruit POPO Tea \u767e\u9999\u51e4\u68a8\u5575\u5575\u8336",
                    "price": "$8.65",
                    "description": "Include: POPO, Fresh Pineapple Jam, Passion Fruit, Lime, Jasmine Tea."
                }
            ]
        },
        {
            "title": "Fresh Fruit Tea (\u4e66\u4ea6\uff0d\u56db\u5b63\u6c34\u679c\u8336)",
            "menu": [
                {
                    "name": "Raw Coconut Mulberry \u751f\u6930\u6851\u845a\u8393\u8393",
                    "price": "$9.85",
                    "description": "Include: Green Tea, Fresh Mulberry, Fresh Strawberry, Coconut Milk"
                }
            ]
        },
        {
            "title": "Fresh Fruit Tea (\u4e66\u4ea6\uff0d\u56db\u5b63\u6c34\u679c\u8336)",
            "menu": [
                {
                    "name": "Raw Coconut Mulberry \u751f\u6930\u6851\u845a\u8393\u8393",
                    "price": "$9.85",
                    "description": "Include: Green Tea, Fresh Mulberry, Fresh Strawberry, Coconut Milk"
                }
            ]
        },
        {
            "title": "Fresh Fruit Tea (\u4e66\u4ea6\uff0d\u56db\u5b63\u6c34\u679c\u8336)",
            "menu": [
                {
                    "name": "Mulberry Green Tea \u6851\u845a\u8393\u8393 (500ml)",
                    "price": "$8.15",
                    "description": "Include: Jasmine Tea, POPO, Fresh Mulberry, Fresh Strawberry, Fresh Lime"
                }
            ]
        },
        {
            "title": "Fresh Fruit Tea (\u4e66\u4ea6\uff0d\u56db\u5b63\u6c34\u679c\u8336)",
            "menu": [
                {
                    "name": "Mulberry Green Tea \u6851\u845a\u8393\u8393 (500ml)",
                    "price": "$8.15",
                    "description": "Include: Jasmine Tea, POPO, Fresh Mulberry, Fresh Strawberry, Fresh Lime"
                }
            ]
        },
        {
            "title": "Fresh Fruit Tea (\u4e66\u4ea6\uff0d\u56db\u5b63\u6c34\u679c\u8336)",
            "menu": [
                {
                    "name": "Chestnut Rose Yakult \u523a\u68a8\u767d\u6708\u5149 (700ml)",
                    "price": "$9.15",
                    "description": "Include: POPO, Chestnut Rose Juice, Fresh Lime, Upgraded Yakult"
                }
            ]
        },
        {
            "title": "Fresh Fruit Tea (\u4e66\u4ea6\uff0d\u56db\u5b63\u6c34\u679c\u8336)",
            "menu": [
                {
                    "name": "Chestnut Rose Yakult \u523a\u68a8\u767d\u6708\u5149 (700ml)",
                    "price": "$9.15",
                    "description": "Include: POPO, Chestnut Rose Juice, Fresh Lime, Upgraded Yakult"
                }
            ]
        },
        {
            "title": "Fresh Fruit Tea (\u4e66\u4ea6\uff0d\u56db\u5b63\u6c34\u679c\u8336)",
            "menu": [
                {
                    "name": "Camellia \u2116 5 \u7ea2\u989c\u523a\u68a8\u6731\u7802\u75e3",
                    "price": "$8.55",
                    "description": "Includes: Camellia Oolong Tea, Coconut Jelly, Kumquat, Strawberry, Chestnut Rose Juice, Snow fungus, Goji Berries"
                }
            ]
        },
        {
            "title": "Fresh Fruit Tea (\u4e66\u4ea6\uff0d\u56db\u5b63\u6c34\u679c\u8336)",
            "menu": [
                {
                    "name": "Camellia \u2116 5 \u7ea2\u989c\u523a\u68a8\u6731\u7802\u75e3",
                    "price": "$8.55",
                    "description": "Includes: Camellia Oolong Tea, Coconut Jelly, Kumquat, Strawberry, Chestnut Rose Juice, Snow fungus, Goji Berries"
                }
            ]
        },
        {
            "title": "Fresh Fruit Tea (\u4e66\u4ea6\uff0d\u56db\u5b63\u6c34\u679c\u8336)",
            "menu": [
                {
                    "name": "Honey Pomelo Tea \u8702\u871c\u67da\u5b50\u8336(600ml)",
                    "price": "$6.95",
                    "description": "Include: Jasmine Tea, Lime, Honey Pomelo.To keep the best quality and taste, for the sugar level of this item, \"no sugar\" is not optional! (\u975e\u5e38\u62b1\u6b49\uff0c\u4e3a\u4e86\u4fdd\u8bc1\u8fd9\u6b3e\u4ea7\u54c1\u7684\u54c1\u8d28\u548c\u5473\u9053\uff0c\u6211\u4eec\u4e0d\u80fd\u5b8c\u5168\u53bb\u7cd6\uff0c\u4f46\u5982\u679c\u60a8\u6709\u7279\u6b8a\u8981\u6c42\u6211\u4eec\u53ef\u4ee5\u4e3a\u60a8\u5c3d\u91cf\u5c11\u7cd6!)"
                }
            ]
        },
        {
            "title": "Fresh Fruit Tea (\u4e66\u4ea6\uff0d\u56db\u5b63\u6c34\u679c\u8336)",
            "menu": [
                {
                    "name": "Honey Pomelo Tea \u8702\u871c\u67da\u5b50\u8336(600ml)",
                    "price": "$6.95",
                    "description": "Include: Jasmine Tea, Lime, Honey Pomelo.To keep the best quality and taste, for the sugar level of this item, \"no sugar\" is not optional! (\u975e\u5e38\u62b1\u6b49\uff0c\u4e3a\u4e86\u4fdd\u8bc1\u8fd9\u6b3e\u4ea7\u54c1\u7684\u54c1\u8d28\u548c\u5473\u9053\uff0c\u6211\u4eec\u4e0d\u80fd\u5b8c\u5168\u53bb\u7cd6\uff0c\u4f46\u5982\u679c\u60a8\u6709\u7279\u6b8a\u8981\u6c42\u6211\u4eec\u53ef\u4ee5\u4e3a\u60a8\u5c3d\u91cf\u5c11\u7cd6!)"
                }
            ]
        },
        {
            "title": "Fresh Fruit Tea (\u4e66\u4ea6\uff0d\u56db\u5b63\u6c34\u679c\u8336)",
            "menu": [
                {
                    "name": "Strawberry Cheese Green Tea \u829d\u58eb\u8349\u8393\u591a\u591a(700ml)",
                    "price": "$9.95",
                    "description": "Include: Fig Jelly, Osmanthus Jelly, Fresh Strawberry, Jasmine Tea, Cheese."
                }
            ]
        },
        {
            "title": "Fresh Fruit Tea (\u4e66\u4ea6\uff0d\u56db\u5b63\u6c34\u679c\u8336)",
            "menu": [
                {
                    "name": "Strawberry Cheese Green Tea \u829d\u58eb\u8349\u8393\u591a\u591a(700ml)",
                    "price": "$9.95",
                    "description": "Include: Fig Jelly, Osmanthus Jelly, Fresh Strawberry, Jasmine Tea, Cheese."
                }
            ]
        },
        {
            "title": "Fresh Fruit Tea (\u4e66\u4ea6\uff0d\u56db\u5b63\u6c34\u679c\u8336)",
            "menu": [
                {
                    "name": "Mango Cheese Green Tea \u829d\u58eb\u8292\u679c\u591a\u591a(700ml)",
                    "price": "$9.95",
                    "description": "Include: Fresh Mango, Jasmine Tea, Cheese"
                }
            ]
        },
        {
            "title": "Fresh Fruit Tea (\u4e66\u4ea6\uff0d\u56db\u5b63\u6c34\u679c\u8336)",
            "menu": [
                {
                    "name": "Mango Cheese Green Tea \u829d\u58eb\u8292\u679c\u591a\u591a(700ml)",
                    "price": "$9.95",
                    "description": "Include: Fresh Mango, Jasmine Tea, Cheese"
                }
            ]
        },
        {
            "title": "Fresh Fruit Tea (\u4e66\u4ea6\uff0d\u56db\u5b63\u6c34\u679c\u8336)",
            "menu": [
                {
                    "name": "Camellia \u21161 \u68a8\u82b1\u98d8\u96ea(500ml)",
                    "price": "$8.25",
                    "description": "Includes: Camellia Oolong Tea, Taro Balls, Snow fungus, Goji Berries"
                }
            ]
        },
        {
            "title": "Fresh Fruit Tea (\u4e66\u4ea6\uff0d\u56db\u5b63\u6c34\u679c\u8336)",
            "menu": [
                {
                    "name": "Camellia \u21161 \u68a8\u82b1\u98d8\u96ea(500ml)",
                    "price": "$8.25",
                    "description": "Includes: Camellia Oolong Tea, Taro Balls, Snow fungus, Goji Berries"
                }
            ]
        },
        {
            "title": "Oolong (\u4e66\u4ea6-\u534a\u5929\u592d\u4e4c\u9f99)",
            "menu": [
                {
                    "name": "Raw Coconut Milk Tea \u751f\u6930\u67e0\u6aac\u649e\u5976(500ml)",
                    "price": "$8.25",
                    "description": "Includes: Bantianyao Oolong Tea, Plant based Milk, Raw Coconut Milk, Fresh LimeTo keep the best quality and taste, \u201cno sugar\u201d is not optional, for the ice level of this item, \"no ice\" is not optional! (\u975e\u5e38\u62b1\u6b49\uff0c\u4e3a\u4e86\u4fdd\u8bc1\u8fd9\u6b3e\u4ea7\u54c1\u7684\u54c1\u8d28\u548c\u5473\u9053\uff0c\u6211\u4eec\u4e0d\u80fd\u5b8c\u5168\u53bb\u7cd6\u548c\u5b8c\u5168\u53bb\u51b0\uff0c\u4f46\u5982\u679c\u60a8\u6709\u7279\u6b8a\u8981\u6c42\u6211\u4eec\u53ef\u4ee5\u4e3a\u60a8\u5c3d\u91cf\u5c11\u7cd6\u4e0e\u5c11\u51b0!)"
                }
            ]
        },
        {
            "title": "Oolong (\u4e66\u4ea6-\u534a\u5929\u592d\u4e4c\u9f99)",
            "menu": [
                {
                    "name": "Raw Coconut Milk Tea \u751f\u6930\u67e0\u6aac\u649e\u5976(500ml)",
                    "price": "$8.25",
                    "description": "Includes: Bantianyao Oolong Tea, Plant based Milk, Raw Coconut Milk, Fresh LimeTo keep the best quality and taste, \u201cno sugar\u201d is not optional, for the ice level of this item, \"no ice\" is not optional! (\u975e\u5e38\u62b1\u6b49\uff0c\u4e3a\u4e86\u4fdd\u8bc1\u8fd9\u6b3e\u4ea7\u54c1\u7684\u54c1\u8d28\u548c\u5473\u9053\uff0c\u6211\u4eec\u4e0d\u80fd\u5b8c\u5168\u53bb\u7cd6\u548c\u5b8c\u5168\u53bb\u51b0\uff0c\u4f46\u5982\u679c\u60a8\u6709\u7279\u6b8a\u8981\u6c42\u6211\u4eec\u53ef\u4ee5\u4e3a\u60a8\u5c3d\u91cf\u5c11\u7cd6\u4e0e\u5c11\u51b0!)"
                }
            ]
        },
        {
            "title": "Oolong (\u4e66\u4ea6-\u534a\u5929\u592d\u4e4c\u9f99)",
            "menu": [
                {
                    "name": "Pure Oolong \u534a\u5929\u592d\u4e4c\u9f99\u8336(700ml)",
                    "price": "$5.35",
                    "description": "Includes: Bantianyao Oolong TeaTo keep the best quality and taste, for the ice level of this item, \"no ice\" is not optional! (\u975e\u5e38\u62b1\u6b49\uff0c\u4e3a\u4e86\u4fdd\u8bc1\u8fd9\u6b3e\u4ea7\u54c1\u7684\u54c1\u8d28\u548c\u5473\u9053\uff0c\u6211\u4eec\u4e0d\u80fd\u5b8c\u5168\u53bb\u51b0\uff0c\u4f46\u5982\u679c\u60a8\u6709\u7279\u6b8a\u8981\u6c42\u6211\u4eec\u53ef\u4ee5\u4e3a\u60a8\u5c3d\u91cf\u5c11\u51b0!)"
                }
            ]
        },
        {
            "title": "Oolong (\u4e66\u4ea6-\u534a\u5929\u592d\u4e4c\u9f99)",
            "menu": [
                {
                    "name": "Pure Oolong \u534a\u5929\u592d\u4e4c\u9f99\u8336(700ml)",
                    "price": "$5.35",
                    "description": "Includes: Bantianyao Oolong TeaTo keep the best quality and taste, for the ice level of this item, \"no ice\" is not optional! (\u975e\u5e38\u62b1\u6b49\uff0c\u4e3a\u4e86\u4fdd\u8bc1\u8fd9\u6b3e\u4ea7\u54c1\u7684\u54c1\u8d28\u548c\u5473\u9053\uff0c\u6211\u4eec\u4e0d\u80fd\u5b8c\u5168\u53bb\u51b0\uff0c\u4f46\u5982\u679c\u60a8\u6709\u7279\u6b8a\u8981\u6c42\u6211\u4eec\u53ef\u4ee5\u4e3a\u60a8\u5c3d\u91cf\u5c11\u51b0!)"
                }
            ]
        },
        {
            "title": "Oolong (\u4e66\u4ea6-\u534a\u5929\u592d\u4e4c\u9f99)",
            "menu": [
                {
                    "name": "Lemon Strawberry Oolong \u9999\u67e0\u8393\u8393\u4e4c\u9f99(500ml)",
                    "price": "$8.25",
                    "description": "Includes: Fresh Lime, Strawberry, Bantianyao OolongTo keep the best quality and taste, \u201cno sugar\u201d is not optional! (\u975e\u5e38\u62b1\u6b49\uff0c\u4e3a\u4e86\u4fdd\u8bc1\u8fd9\u6b3e\u4ea7\u54c1\u7684\u54c1\u8d28\u548c\u5473\u9053\uff0c\u6211\u4eec\u4e0d\u80fd\u5b8c\u5168\u53bb\u7cd6\uff0c\u4f46\u5982\u679c\u60a8\u6709\u7279\u6b8a\u8981\u6c42\u6211\u4eec\u53ef\u4ee5\u4e3a\u60a8\u5c3d\u91cf\u5c11\u7cd6!)"
                }
            ]
        },
        {
            "title": "Oolong (\u4e66\u4ea6-\u534a\u5929\u592d\u4e4c\u9f99)",
            "menu": [
                {
                    "name": "Lemon Strawberry Oolong \u9999\u67e0\u8393\u8393\u4e4c\u9f99(500ml)",
                    "price": "$8.25",
                    "description": "Includes: Fresh Lime, Strawberry, Bantianyao OolongTo keep the best quality and taste, \u201cno sugar\u201d is not optional! (\u975e\u5e38\u62b1\u6b49\uff0c\u4e3a\u4e86\u4fdd\u8bc1\u8fd9\u6b3e\u4ea7\u54c1\u7684\u54c1\u8d28\u548c\u5473\u9053\uff0c\u6211\u4eec\u4e0d\u80fd\u5b8c\u5168\u53bb\u7cd6\uff0c\u4f46\u5982\u679c\u60a8\u6709\u7279\u6b8a\u8981\u6c42\u6211\u4eec\u53ef\u4ee5\u4e3a\u60a8\u5c3d\u91cf\u5c11\u7cd6!)"
                }
            ]
        },
        {
            "title": "Oolong (\u4e66\u4ea6-\u534a\u5929\u592d\u4e4c\u9f99)",
            "menu": [
                {
                    "name": "Brown Sugar Oolong \u9ed1\u7cd6\u73cd\u73e0\u4e4c\u9f99(500ml)",
                    "price": "$7.45",
                    "description": "Includes: Bantianyao Oolong Tea, Plant based Milk, Brown Sugar Tapioca"
                }
            ]
        },
        {
            "title": "Oolong (\u4e66\u4ea6-\u534a\u5929\u592d\u4e4c\u9f99)",
            "menu": [
                {
                    "name": "Brown Sugar Oolong \u9ed1\u7cd6\u73cd\u73e0\u4e4c\u9f99(500ml)",
                    "price": "$7.45",
                    "description": "Includes: Bantianyao Oolong Tea, Plant based Milk, Brown Sugar Tapioca"
                }
            ]
        },
        {
            "title": "Oolong (\u4e66\u4ea6-\u534a\u5929\u592d\u4e4c\u9f99)",
            "menu": [
                {
                    "name": "Plant Milk Oolong \u4e4c\u9f99\u690d\u4e73\u8336(500ml)",
                    "price": "$6.65",
                    "description": "Includes: Plant Milk, Bantianyao Oolong TeaTo keep the best quality and taste, \u201cno sugar\u201d is not optional! (\u975e\u5e38\u62b1\u6b49\uff0c\u4e3a\u4e86\u4fdd\u8bc1\u8fd9\u6b3e\u4ea7\u54c1\u7684\u54c1\u8d28\u548c\u5473\u9053\uff0c\u6211\u4eec\u4e0d\u80fd\u5b8c\u5168\u53bb\u7cd6\uff0c\u4f46\u5982\u679c\u60a8\u6709\u7279\u6b8a\u8981\u6c42\u6211\u4eec\u53ef\u4ee5\u4e3a\u60a8\u5c3d\u91cf\u5c11\u7cd6!)"
                }
            ]
        },
        {
            "title": "Oolong (\u4e66\u4ea6-\u534a\u5929\u592d\u4e4c\u9f99)",
            "menu": [
                {
                    "name": "Plant Milk Oolong \u4e4c\u9f99\u690d\u4e73\u8336(500ml)",
                    "price": "$6.65",
                    "description": "Includes: Plant Milk, Bantianyao Oolong TeaTo keep the best quality and taste, \u201cno sugar\u201d is not optional! (\u975e\u5e38\u62b1\u6b49\uff0c\u4e3a\u4e86\u4fdd\u8bc1\u8fd9\u6b3e\u4ea7\u54c1\u7684\u54c1\u8d28\u548c\u5473\u9053\uff0c\u6211\u4eec\u4e0d\u80fd\u5b8c\u5168\u53bb\u7cd6\uff0c\u4f46\u5982\u679c\u60a8\u6709\u7279\u6b8a\u8981\u6c42\u6211\u4eec\u53ef\u4ee5\u4e3a\u60a8\u5c3d\u91cf\u5c11\u7cd6!)"
                }
            ]
        }
    ]
}